{
	"archive" : {},
	"artifacts" : 
	[
		{
			"path" : "pix/curlpp/libcurlpp_st.a"
		}
	],
	"backtrace" : 1,
	"backtraceGraph" : 
	{
		"commands" : 
		[
			"add_library",
			"add_definitions",
			"target_include_directories"
		],
		"files" : 
		[
			"pix/curlpp/CMakeLists.txt",
			"pix/CMakeLists.txt",
			"CMakeLists.txt"
		],
		"nodes" : 
		[
			{
				"file" : 0
			},
			{
				"command" : 0,
				"file" : 0,
				"line" : 42,
				"parent" : 0
			},
			{
				"file" : 1
			},
			{
				"command" : 1,
				"file" : 1,
				"line" : 6,
				"parent" : 2
			},
			{
				"file" : 2
			},
			{
				"command" : 1,
				"file" : 2,
				"line" : 4,
				"parent" : 4
			},
			{
				"command" : 2,
				"file" : 0,
				"line" : 80,
				"parent" : 0
			}
		]
	},
	"compileGroups" : 
	[
		{
			"compileCommandFragments" : 
			[
				{
					"fragment" : "-O3 -DNDEBUG -std=gnu++2b -fcolor-diagnostics"
				}
			],
			"defines" : 
			[
				{
					"backtrace" : 3,
					"define" : "CURL_STATICLIB"
				},
				{
					"backtrace" : 5,
					"define" : "NAPI_VERSION=4"
				}
			],
			"includes" : 
			[
				{
					"backtrace" : 6,
					"path" : "C:/Users/Administrator/CLionProjects/PixJS/pix/curlpp/include"
				}
			],
			"language" : "CXX",
			"languageStandard" : 
			{
				"backtraces" : 
				[
					1
				],
				"standard" : "23"
			},
			"sourceIndexes" : 
			[
				34,
				35,
				36,
				37,
				38,
				39,
				40,
				41,
				42,
				43,
				44,
				45
			]
		}
	],
	"id" : "curlpp_st::@59424ddaa20238f42788",
	"name" : "curlpp_st",
	"nameOnDisk" : "libcurlpp_st.a",
	"paths" : 
	{
		"build" : "pix/curlpp",
		"source" : "pix/curlpp"
	},
	"sourceGroups" : 
	[
		{
			"name" : "Header Files",
			"sourceIndexes" : 
			[
				0,
				1,
				2,
				3,
				4,
				5,
				6,
				7,
				8,
				9,
				10,
				11,
				12,
				13,
				14,
				15,
				16,
				17,
				18,
				19,
				20,
				21,
				22,
				23,
				24,
				25,
				26,
				27,
				28,
				29,
				30,
				31,
				32,
				33
			]
		},
		{
			"name" : "Source Files",
			"sourceIndexes" : 
			[
				34,
				35,
				36,
				37,
				38,
				39,
				40,
				41,
				42,
				43,
				44,
				45
			]
		}
	],
	"sources" : 
	[
		{
			"backtrace" : 1,
			"path" : "pix/curlpp/include/curlpp/Easy.hpp",
			"sourceGroupIndex" : 0
		},
		{
			"backtrace" : 1,
			"path" : "pix/curlpp/include/curlpp/Easy.inl",
			"sourceGroupIndex" : 0
		},
		{
			"backtrace" : 1,
			"path" : "pix/curlpp/include/curlpp/Exception.hpp",
			"sourceGroupIndex" : 0
		},
		{
			"backtrace" : 1,
			"path" : "pix/curlpp/include/curlpp/Form.hpp",
			"sourceGroupIndex" : 0
		},
		{
			"backtrace" : 1,
			"path" : "pix/curlpp/include/curlpp/Info.hpp",
			"sourceGroupIndex" : 0
		},
		{
			"backtrace" : 1,
			"path" : "pix/curlpp/include/curlpp/Info.inl",
			"sourceGroupIndex" : 0
		},
		{
			"backtrace" : 1,
			"path" : "pix/curlpp/include/curlpp/Infos.hpp",
			"sourceGroupIndex" : 0
		},
		{
			"backtrace" : 1,
			"path" : "pix/curlpp/include/curlpp/Multi.hpp",
			"sourceGroupIndex" : 0
		},
		{
			"backtrace" : 1,
			"path" : "pix/curlpp/include/curlpp/Option.hpp",
			"sourceGroupIndex" : 0
		},
		{
			"backtrace" : 1,
			"path" : "pix/curlpp/include/curlpp/Option.inl",
			"sourceGroupIndex" : 0
		},
		{
			"backtrace" : 1,
			"path" : "pix/curlpp/include/curlpp/OptionBase.hpp",
			"sourceGroupIndex" : 0
		},
		{
			"backtrace" : 1,
			"path" : "pix/curlpp/include/curlpp/Options.hpp",
			"sourceGroupIndex" : 0
		},
		{
			"backtrace" : 1,
			"path" : "pix/curlpp/include/curlpp/Types.hpp",
			"sourceGroupIndex" : 0
		},
		{
			"backtrace" : 1,
			"path" : "pix/curlpp/include/curlpp/cURLpp.hpp",
			"sourceGroupIndex" : 0
		},
		{
			"backtrace" : 1,
			"path" : "pix/curlpp/include/curlpp/internal/CurlHandle.hpp",
			"sourceGroupIndex" : 0
		},
		{
			"backtrace" : 1,
			"path" : "pix/curlpp/include/curlpp/internal/CurlHandle.inl",
			"sourceGroupIndex" : 0
		},
		{
			"backtrace" : 1,
			"path" : "pix/curlpp/include/curlpp/internal/OptionContainer.hpp",
			"sourceGroupIndex" : 0
		},
		{
			"backtrace" : 1,
			"path" : "pix/curlpp/include/curlpp/internal/OptionContainer.inl",
			"sourceGroupIndex" : 0
		},
		{
			"backtrace" : 1,
			"path" : "pix/curlpp/include/curlpp/internal/OptionContainerType.hpp",
			"sourceGroupIndex" : 0
		},
		{
			"backtrace" : 1,
			"path" : "pix/curlpp/include/curlpp/internal/OptionList.hpp",
			"sourceGroupIndex" : 0
		},
		{
			"backtrace" : 1,
			"path" : "pix/curlpp/include/curlpp/internal/OptionSetter.hpp",
			"sourceGroupIndex" : 0
		},
		{
			"backtrace" : 1,
			"path" : "pix/curlpp/include/curlpp/internal/OptionSetter.inl",
			"sourceGroupIndex" : 0
		},
		{
			"backtrace" : 1,
			"path" : "pix/curlpp/include/curlpp/internal/SList.hpp",
			"sourceGroupIndex" : 0
		},
		{
			"backtrace" : 1,
			"path" : "pix/curlpp/include/utilspp/EmptyType.hpp",
			"sourceGroupIndex" : 0
		},
		{
			"backtrace" : 1,
			"path" : "pix/curlpp/include/utilspp/NonCopyable.hpp",
			"sourceGroupIndex" : 0
		},
		{
			"backtrace" : 1,
			"path" : "pix/curlpp/include/utilspp/NullType.hpp",
			"sourceGroupIndex" : 0
		},
		{
			"backtrace" : 1,
			"path" : "pix/curlpp/include/utilspp/SmartPtr.hpp",
			"sourceGroupIndex" : 0
		},
		{
			"backtrace" : 1,
			"path" : "pix/curlpp/include/utilspp/ThreadingFactoryMutex.hpp",
			"sourceGroupIndex" : 0
		},
		{
			"backtrace" : 1,
			"path" : "pix/curlpp/include/utilspp/ThreadingFactoryMutex.inl",
			"sourceGroupIndex" : 0
		},
		{
			"backtrace" : 1,
			"path" : "pix/curlpp/include/utilspp/ThreadingSingle.hpp",
			"sourceGroupIndex" : 0
		},
		{
			"backtrace" : 1,
			"path" : "pix/curlpp/include/utilspp/ThreadingSingle.inl",
			"sourceGroupIndex" : 0
		},
		{
			"backtrace" : 1,
			"path" : "pix/curlpp/include/utilspp/TypeList.hpp",
			"sourceGroupIndex" : 0
		},
		{
			"backtrace" : 1,
			"path" : "pix/curlpp/include/utilspp/TypeTrait.hpp",
			"sourceGroupIndex" : 0
		},
		{
			"backtrace" : 1,
			"path" : "pix/curlpp/include/utilspp/clone_ptr.hpp",
			"sourceGroupIndex" : 0
		},
		{
			"backtrace" : 1,
			"compileGroupIndex" : 0,
			"path" : "pix/curlpp/src/curlpp/Easy.cpp",
			"sourceGroupIndex" : 1
		},
		{
			"backtrace" : 1,
			"compileGroupIndex" : 0,
			"path" : "pix/curlpp/src/curlpp/Exception.cpp",
			"sourceGroupIndex" : 1
		},
		{
			"backtrace" : 1,
			"compileGroupIndex" : 0,
			"path" : "pix/curlpp/src/curlpp/Form.cpp",
			"sourceGroupIndex" : 1
		},
		{
			"backtrace" : 1,
			"compileGroupIndex" : 0,
			"path" : "pix/curlpp/src/curlpp/Info.cpp",
			"sourceGroupIndex" : 1
		},
		{
			"backtrace" : 1,
			"compileGroupIndex" : 0,
			"path" : "pix/curlpp/src/curlpp/Multi.cpp",
			"sourceGroupIndex" : 1
		},
		{
			"backtrace" : 1,
			"compileGroupIndex" : 0,
			"path" : "pix/curlpp/src/curlpp/OptionBase.cpp",
			"sourceGroupIndex" : 1
		},
		{
			"backtrace" : 1,
			"compileGroupIndex" : 0,
			"path" : "pix/curlpp/src/curlpp/Options.cpp",
			"sourceGroupIndex" : 1
		},
		{
			"backtrace" : 1,
			"compileGroupIndex" : 0,
			"path" : "pix/curlpp/src/curlpp/cURLpp.cpp",
			"sourceGroupIndex" : 1
		},
		{
			"backtrace" : 1,
			"compileGroupIndex" : 0,
			"path" : "pix/curlpp/src/curlpp/internal/CurlHandle.cpp",
			"sourceGroupIndex" : 1
		},
		{
			"backtrace" : 1,
			"compileGroupIndex" : 0,
			"path" : "pix/curlpp/src/curlpp/internal/OptionList.cpp",
			"sourceGroupIndex" : 1
		},
		{
			"backtrace" : 1,
			"compileGroupIndex" : 0,
			"path" : "pix/curlpp/src/curlpp/internal/OptionSetter.cpp",
			"sourceGroupIndex" : 1
		},
		{
			"backtrace" : 1,
			"compileGroupIndex" : 0,
			"path" : "pix/curlpp/src/curlpp/internal/SList.cpp",
			"sourceGroupIndex" : 1
		}
	],
	"type" : "STATIC_LIBRARY"
}
